greeter/__init__.py
greeter/cli.py
greeter_test_elated_swanson-0.1.0.dist-info/METADATA
greeter_test_elated_swanson-0.1.0.dist-info/WHEEL
greeter_test_elated_swanson-0.1.0.dist-info/entry_points.txt
greeter_test_elated_swanson-0.1.0.dist-info/RECORD
