Metadata-Version: 2.1
Name: greeter-test-elated-swanson
Version: 0.1.0
Summary: 
Author: Diego Quintana
Author-email: diego.quintana@somenergia.coop
Requires-Python: >=3.10,<4.0
Classifier: Programming Language :: Python :: 3
Classifier: Programming Language :: Python :: 3.10
Classifier: Programming Language :: Python :: 3.11
Requires-Dist: cowsay (>=6.1,<7.0)
